compose_runner/__init__.py
compose_runner/_version.py
compose_runner/cli.py
compose_runner/ecs_task.py
compose_runner/run.py
compose_runner/sentry.py
compose_runner/aws_lambda/__init__.py
compose_runner/aws_lambda/common.py
compose_runner/aws_lambda/cost_check_handler.py
compose_runner/aws_lambda/log_poll_handler.py
compose_runner/aws_lambda/results_handler.py
compose_runner/aws_lambda/run_handler.py
compose_runner/aws_lambda/status_handler.py
compose_runner/tests/conftest.py
compose_runner/tests/test_cli.py
compose_runner/tests/test_ecs_task.py
compose_runner/tests/test_lambda_handlers.py
compose_runner/tests/test_run.py
compose_runner/tests/cassettes/test_lambda_handlers/test_select_task_size_uses_large_for_montecarlo.yaml
compose_runner/tests/cassettes/test_lambda_handlers/test_select_task_size_uses_standard_for_fdr.yaml
compose_runner/tests/cassettes/test_run/test_download_bundle.yaml
compose_runner/tests/cassettes/test_run/test_run_database_workflow.yaml
compose_runner/tests/cassettes/test_run/test_run_group_comparison_workflow.yaml
compose_runner/tests/cassettes/test_run/test_run_string_group_comparison_workflow.yaml
compose_runner/tests/cassettes/test_run/test_run_workflow.yaml
compose_runner-0.7.1.dist-info/METADATA
compose_runner-0.7.1.dist-info/WHEEL
compose_runner-0.7.1.dist-info/entry_points.txt
compose_runner-0.7.1.dist-info/licenses/LICENSE
compose_runner-0.7.1.dist-info/RECORD
