Metadata-Version: 2.4
Name: compose-runner
Version: 0.7.1
Summary: A package for running neurosynth-compose analyses
Project-URL: Repository, https://github.com/neurostuff/compose-runner
Author-email: James Kent <jamesdkent21@gmail.com>
License: BSD 3-Clause License
License-File: LICENSE
Keywords: meta-analysis,neuroimaging,neurosynth,neurosynth-compose
Classifier: License :: OSI Approved :: BSD License
Classifier: Programming Language :: Python :: 3
Requires-Dist: click
Requires-Dist: nimare>=0.7.0
Requires-Dist: numpy
Requires-Dist: sentry-sdk
Provides-Extra: aws
Requires-Dist: boto3; extra == 'aws'
Provides-Extra: tests
Requires-Dist: pytest; extra == 'tests'
Requires-Dist: pytest-recording; extra == 'tests'
Requires-Dist: vcrpy; extra == 'tests'
